LICENSE
MANIFEST.in
README.md
requirements.txt
setup.cfg
setup.py
calvestbr/__init__.py
calvestbr/calvestbr.py
calvestbr.egg-info/PKG-INFO
calvestbr.egg-info/SOURCES.txt
calvestbr.egg-info/dependency_links.txt
calvestbr.egg-info/not-zip-safe
calvestbr.egg-info/top_level.txt