Metadata-Version: 2.1
Name: calvestbr
Version: 0.0.1
Summary: Este Framework tem o objetivo de auxiliar os jovens estudantes que estão prestes a ingressar na universidade a se organizarem quanto as datas de vestibulares.
Home-page: https://github.com/Marina-Lara/calvestbr
Author: Ana_Isaac_Marina
Author-email: marinalara170303@gmail.com
License: MIT license
Keywords: calvestbr
Platform: UNKNOWN
Classifier: Development Status :: 2 - Pre-Alpha
Classifier: Intended Audience :: Developers
Classifier: License :: OSI Approved :: MIT License
Classifier: Natural Language :: English
Classifier: Programming Language :: Python :: 3
Classifier: Programming Language :: Python :: 3.5
Classifier: Programming Language :: Python :: 3.6
Classifier: Programming Language :: Python :: 3.7
Classifier: Programming Language :: Python :: 3.8
Requires-Python: >=3.5
